MANIFEST.in
setup.py
src/__init__.py
src/gen/__init__.py
src/gen/twitter/__init__.py
src/gen/twitter/thrift/__init__.py
src/gen/twitter/thrift/endpoint/__init__.py
src/gen/twitter/thrift/endpoint/constants.py
src/gen/twitter/thrift/endpoint/ttypes.py
src/twitter.common.service_thrift.egg-info/PKG-INFO
src/twitter.common.service_thrift.egg-info/SOURCES.txt
src/twitter.common.service_thrift.egg-info/dependency_links.txt
src/twitter.common.service_thrift.egg-info/namespace_packages.txt
src/twitter.common.service_thrift.egg-info/top_level.txt
src/twitter.common.service_thrift.egg-info/zip-safe