Metadata-Version: 1.1
Name: twitter.common.service-thrift
Version: 0.3.4
Summary: twitter.common thrift stubs for metadata used with Twitter's service discovery libraries.
Home-page: https://github.com/twitter/commons
Author: UNKNOWN
Author-email: UNKNOWN
License: Apache License, Version 2.0
Platform: UNKNOWN
Classifier: Intended Audience :: Developers
Classifier: License :: OSI Approved :: Apache Software License
Classifier: Operating System :: OS Independent
Classifier: Programming Language :: Python
